monepy/__init__.py
monepy/utils.py
monepy/currency/__init__.py
monepy/currency/base.py
monepy/exceptions/__init__.py
monepy-0.4.dist-info/METADATA
monepy-0.4.dist-info/WHEEL
monepy-0.4.dist-info/licenses/LICENSE
monepy-0.4.dist-info/RECORD
