Metadata-Version: 2.4
Name: Monepy
Version: 0.4
Summary: Currency classes to work with monetary values
Project-URL: Documentation, https://vsbits.net/monepy/
Project-URL: Repository, https://github.com/vsbits/monepy
Project-URL: Issues, https://github.com/vsbits/monepy/issues
Author-email: Vítor dos Santos Araujo <vitoraraujo@tuta.com>
License-Expression: MIT
License-File: LICENSE
Requires-Python: >=3.11
Provides-Extra: tests
Requires-Dist: flake8; extra == 'tests'
Requires-Dist: mypy; extra == 'tests'
Requires-Dist: pandas; extra == 'tests'
Requires-Dist: pytest; extra == 'tests'
Requires-Dist: pytest-cov; extra == 'tests'
